LICENSE.txt
README.md
setup.cfg
setup.py
StableSwapPy.egg-info/PKG-INFO
StableSwapPy.egg-info/SOURCES.txt
StableSwapPy.egg-info/dependency_links.txt
StableSwapPy.egg-info/not-zip-safe
StableSwapPy.egg-info/requires.txt
StableSwapPy.egg-info/top_level.txt
python/prod/__init__.py
python/prod/cst/exchg/StableswapExchange.py
python/prod/cst/exchg/StableswapPoolMath.py
python/prod/cst/exchg/__init__.py
python/prod/cst/factory/StableswapFactory.py
python/prod/cst/factory/__init__.py
python/prod/erc/ERC20.py
python/prod/erc/__init__.py
python/prod/process/join/Join.py
python/prod/process/join/__init__.py
python/prod/process/liquidity/AddLiquidity.py
python/prod/process/liquidity/RemoveLiquidity.py
python/prod/process/liquidity/__init__.py
python/prod/process/swap/Swap.py
python/prod/process/swap/__init__.py
python/prod/quote/CSQuote.py
python/prod/quote/__init__.py
python/prod/utils/data/ExchangeData.py
python/prod/utils/data/FactoryData.py
python/prod/utils/data/StableswapExchangeData.py
python/prod/utils/data/__init__.py
python/prod/utils/interfaces/IExchange.py
python/prod/utils/interfaces/IExchangeFactory.py
python/prod/utils/interfaces/__init__.py
python/prod/vault/StableswapVault.py
python/prod/vault/__init__.py